autoserver/__init__.py
autoserver/resources/__init__.py
autoserver/resources/frontfunc.html.jinja2
autoserver/resources/homepage.html.jinja2
autoserver-0.1.0.dist-info/WHEEL
autoserver-0.1.0.dist-info/METADATA
autoserver-0.1.0.dist-info/RECORD
