Metadata-Version: 2.1
Name: autoserver
Version: 0.1.0
Summary: 
Author: JanukanS
Author-email: 28988453+JanukanS@users.noreply.github.com
Requires-Python: >=3.8,<4.0
Classifier: Programming Language :: Python :: 3
Classifier: Programming Language :: Python :: 3.8
Classifier: Programming Language :: Python :: 3.9
Classifier: Programming Language :: Python :: 3.10
Classifier: Programming Language :: Python :: 3.11
Requires-Dist: docstring-parser (>=0.15,<0.16)
Requires-Dist: fastapi (>=0.88.0,<0.89.0)
Requires-Dist: jinja2 (>=3.1.2,<4.0.0)
Requires-Dist: python-multipart (>=0.0.5,<0.0.6)
Requires-Dist: uvicorn (>=0.20.0,<0.21.0)
